vto_geodat/__init__.py
vto_geodat/apps.py
vto_geodat/urls.py
vto_geodat/admin/__init__.py
vto_geodat/admin/tz_a.py
vto_geodat/migrations/0001_initial.py
vto_geodat/migrations/__init__.py
vto_geodat/models/__init__.py
vto_geodat/models/tz_m.py
vto_geodat/models/xyz_m.py
vto_geodat/templates/geodat/tz_list.dtl
vto_geodat/views/__init__.py
vto_geodat/views/tz_v.py
vto_geodat-0.0.2.4.dist-info/METADATA
vto_geodat-0.0.2.4.dist-info/WHEEL
vto_geodat-0.0.2.4.dist-info/licenses/LICENSE
vto_geodat-0.0.2.4.dist-info/RECORD
