Metadata-Version: 2.4
Name: vto-geodat
Version: 0.0.2.4
Summary: Just a personal test app, not intended for use by anyone else
License-Expression: MIT
License-File: LICENSE
Requires-Python: >=3.13
